popip/__init__.py
popip/api/__init__.py
popip/api/api.py
popip/lib/__init__.py
tests/__init__.py
tests/test_pip.py
popip-0.0.2.dist-info/LICENSE
popip-0.0.2.dist-info/METADATA
popip-0.0.2.dist-info/WHEEL
popip-0.0.2.dist-info/top_level.txt
popip-0.0.2.dist-info/RECORD
