Metadata-Version: 2.1
Name: popip
Version: 0.0.2
Summary: pip install popip
Home-page: https://www.python-office.com/
Author: CoderWanFeng
Author-email: 1957875073@qq.com
License: MIT
Project-URL: Bug Tracker, https://github.com/CoderWanFeng/popip/issues
Project-URL: Documentation, https://github.com/CoderWanFeng/popip/blob/master/README.md
Project-URL: Source Code, https://github.com/CoderWanFeng/popip
Platform: any
Requires-Python: >=3.6
License-File: LICENSE
Requires-Dist: pypistats
